LICENSE
MANIFEST.in
setup.py
dark_minimal_dirtree/__init__.py
dark_minimal_dirtree/index.html
dark_minimal_dirtree/main.html
dark_minimal_dirtree/mkdocs_theme.yml
dark_minimal_dirtree/nav-item2.html
dark_minimal_dirtree/nav.html
dark_minimal_dirtree/theme.css
dark_minimal_dirtree/theme.js
dark_minimal_dirtree/highlight/highlight.js
dark_minimal_dirtree/highlight/highlight.min.js
dark_minimal_dirtree/highlight/es/core.js
dark_minimal_dirtree/highlight/es/core.min.js
dark_minimal_dirtree/highlight/es/highlight.js
dark_minimal_dirtree/highlight/es/languages/1c.min.js
dark_minimal_dirtree/highlight/es/languages/abnf.min.js
dark_minimal_dirtree/highlight/es/languages/accesslog.min.js
dark_minimal_dirtree/highlight/es/languages/actionscript.min.js
dark_minimal_dirtree/highlight/es/languages/ada.min.js
dark_minimal_dirtree/highlight/es/languages/angelscript.min.js
dark_minimal_dirtree/highlight/es/languages/apache.min.js
dark_minimal_dirtree/highlight/es/languages/applescript.min.js
dark_minimal_dirtree/highlight/es/languages/arcade.min.js
dark_minimal_dirtree/highlight/es/languages/arduino.min.js
dark_minimal_dirtree/highlight/es/languages/armasm.min.js
dark_minimal_dirtree/highlight/es/languages/asciidoc.min.js
dark_minimal_dirtree/highlight/es/languages/aspectj.min.js
dark_minimal_dirtree/highlight/es/languages/autohotkey.min.js
dark_minimal_dirtree/highlight/es/languages/autoit.min.js
dark_minimal_dirtree/highlight/es/languages/avrasm.min.js
dark_minimal_dirtree/highlight/es/languages/awk.min.js
dark_minimal_dirtree/highlight/es/languages/axapta.min.js
dark_minimal_dirtree/highlight/es/languages/bash.min.js
dark_minimal_dirtree/highlight/es/languages/basic.min.js
dark_minimal_dirtree/highlight/es/languages/bnf.min.js
dark_minimal_dirtree/highlight/es/languages/brainfuck.min.js
dark_minimal_dirtree/highlight/es/languages/c.min.js
dark_minimal_dirtree/highlight/es/languages/cal.min.js
dark_minimal_dirtree/highlight/es/languages/capnproto.min.js
mkdocs_dark_minimal_dirtree.egg-info/PKG-INFO
mkdocs_dark_minimal_dirtree.egg-info/SOURCES.txt
mkdocs_dark_minimal_dirtree.egg-info/dependency_links.txt
mkdocs_dark_minimal_dirtree.egg-info/entry_points.txt
mkdocs_dark_minimal_dirtree.egg-info/not-zip-safe
mkdocs_dark_minimal_dirtree.egg-info/top_level.txt